{
  "$schema": "https://raw.githubusercontent.com/Monster-Train-2-Modding-Group/Trainworks-Reloaded/refs/heads/main/schemas/schemas/cards.json",
  "cards": [
    {
      "id": "Sw_Sherbetrus",
      "names": {
        "english": "Sherbetrus",
        "chinese": "果子露"
      },
      "card_art": "@CardArt_unit_16",
      "cost": 3,
      "card_type": "monster",
      "rarity": "uncommon",
      "class": "@ClassSweetkin",
      "targets_room": true,
      "effects": [
        {
          "id": "@SpawnSherbetrus"
        }
      ],
      "lore_tooltips": [
        {
          "english": "'Symbolism also helps with how a living being should act. You might not know this creature since it inhabits a different version of Hell.'-Rosette"
        }
      ],
      "pools": [
        "UnitsAllBanner"
      ]
    }
  ],
  "characters": [
    {
      "id": "Sherbetrus",
      "size": 3,
      "attack_damage": 15,
      "health": 120,
      "names": {
        "english": "Sherbetrus",
        "chinese": "果子露"
      },
      "character_art": "@SherbetArt",
      "chatter": "@CTR_sherberus",
      "subtypes": [
        "@Sub_Minty",
        "SubtypesData_Snack",
        "SubtypesData_BannerUnit"
      ],
      "starting_status_effects": [
        {
          "status": "eatmany",
          "count": 8
        }
      ],
      "triggers": [
        {
          "id": "@Eat_sherbet"
        }
      ]
    }
  ],
  "character_triggers": [
    {
      "id": "Eat_sherbet",
      "trigger": "on_eaten",
      "descriptions": {
        "english": "Apply Root [effect0.status0.power] to all enemies.",
        "chinese": "对所有敌方单位施加<b>缠绕</b> [effect0.status0.power]。"
      },
      "effects": [
        {
          "id": "@ApplyStatus_sherbet"
        }
      ]
    }
  ],
  "effects": [
    {
      "id": "SpawnSherbetrus",
      "name": "CardEffectSpawnMonster",
      "target_mode": "room",
      "target_card_type": "spell",
      "param_character": "@Sherbetrus"
    },
    {
      "id": "ApplyStatus_sherbet",
      "name": "CardEffectAddStatusEffect",
      "target_mode": "room",
      "target_team": "heroes",
      "param_status_effects": [
        {
          "status": "rooted",
          "count": 1
        }
      ]
    }
  ],
  "sprites": [
    {
      "id": "CardArt_unit_16",
      "path": "textures/CardAssets/Unit_16.png"
    },
    {
      "id": "SherbetArt",
      "path": "textures/UnitAssets/cerberus.png"
    }
  ],
  "game_objects": [
    {
      "id": "CardArt_unit_16",
      "type": "card_art",
      "extensions": {
        "card_art": {
          "sprite": "@CardArt_unit_16"
        }
      }
    },
    {
      "id": "SherbetArt",
      "type": "character_art",
      "extensions": {
        "character_art": {
          "sprite": "@SherbetArt",
          "transform": {
            "position": {
              "x": 0,
              "y": 1.3,
              "z": 0
            },
            "scale": {
              "x": 1.5,
              "y": 1.5,
              "z": 1.5
            }
          }
        }
      }
    }
  ],
  "chatter": [
    {
      "id": "CTR_sherberus",
      "gender": "neutral",
      "added_expressions": [
        {
          "english": "Awoooooooooooooo!"
        },
        {
          "english": "BARK! BARK!"
        }
      ],
      "idle_expressions": [
        {
          "english": "Awoooooooooooooo!"
        },
        {
          "english": "BARK! BARK!"
        }
      ]
    }
  ]
}